sharedfile.cp314t-win32.pyd
sharedfile-0.8.dist-info/licenses/LICENSE
sharedfile-0.8.dist-info/METADATA
sharedfile-0.8.dist-info/WHEEL
sharedfile-0.8.dist-info/top_level.txt
sharedfile-0.8.dist-info/RECORD
