Metadata-Version: 2.4
Name: sharedfile
Version: 0.8
Summary: Cross-platform shared file open with share flags
Home-page: https://github.com/janbremec/sharedfile
Author: Jan Bremec
Author-email: jan04bremec@gmail.com
License: Apache-2.0
Classifier: Programming Language :: Python :: 3
Classifier: Programming Language :: C
Classifier: License :: OSI Approved :: Apache Software License
License-File: LICENSE
Dynamic: author
Dynamic: author-email
Dynamic: classifier
Dynamic: description
Dynamic: description-content-type
Dynamic: home-page
Dynamic: license
Dynamic: license-file
Dynamic: summary
